[
  {
    "key": "mustard",
    "groundRGB": [
      249,
      228,
      215
    ],
    "foilRGB": [
      121,
      83,
      28
    ],
    "sentenceNavy": 12.61,
    "foilGoldActual": 5.58,
    "sentencePassAA": true,
    "foilPassAA": true
  },
  {
    "key": "red",
    "groundRGB": [
      244,
      228,
      218
    ],
    "foilRGB": [
      119,
      92,
      37
    ],
    "sentenceNavy": 12.5,
    "foilGoldActual": 5.07,
    "sentencePassAA": true,
    "foilPassAA": true
  },
  {
    "key": "blonde",
    "groundRGB": [
      233,
      232,
      228
    ],
    "foilRGB": [
      129,
      89,
      36
    ],
    "sentenceNavy": 12.63,
    "foilGoldActual": 5.06,
    "sentencePassAA": true,
    "foilPassAA": true
  },
  {
    "key": "green",
    "groundRGB": [
      234,
      230,
      227
    ],
    "foilRGB": [
      118,
      89,
      33
    ],
    "sentenceNavy": 12.48,
    "foilGoldActual": 5.25,
    "sentencePassAA": true,
    "foilPassAA": true
  }
]